stensorflow/__init__.py
stensorflow/global_var.py
stensorflow/basic/__init__.py
stensorflow/basic/basic_class/__init__.py
stensorflow/basic/basic_class/base.py
stensorflow/basic/basic_class/bitwise.py
stensorflow/basic/basic_class/pair.py
stensorflow/basic/basic_class/private.py
stensorflow/basic/basic_class/share.py
stensorflow/basic/operator/__init__.py
stensorflow/basic/operator/algebra.py
stensorflow/basic/operator/argmax.py
stensorflow/basic/operator/arithmetic.py
stensorflow/basic/operator/conv2dop.py
stensorflow/basic/operator/inverse_sqrt.py
stensorflow/basic/operator/logical.py
stensorflow/basic/operator/order.py
stensorflow/basic/operator/poolingop.py
stensorflow/basic/operator/relu.py
stensorflow/basic/operator/selectshare.py
stensorflow/basic/operator/sigmoid.py
stensorflow/basic/operator/softmax.py
stensorflow/basic/protocol/__init__.py
stensorflow/basic/protocol/bilinear_map.py
stensorflow/basic/protocol/bilinear_triangle.py
stensorflow/basic/protocol/compare.py
stensorflow/basic/protocol/fnz.py
stensorflow/basic/protocol/module_transform.py
stensorflow/basic/protocol/msb.py
stensorflow/basic/protocol/ot.py
stensorflow/basic/protocol/pm1_act.py
stensorflow/basic/protocol/shift.py
stensorflow/basic/sparse/__init__.py
stensorflow/basic/sparse/read_libsvm.py
stensorflow/cops/__init__.py
stensorflow/cops/_stf_INT64Conv2D_macos.so
stensorflow/cops/_stf_homo_linux.so
stensorflow/cops/_stf_homo_macos.so
stensorflow/cops/_stf_int64conv2d_linux.so
stensorflow/cops/_stf_int64pooling_linux.so
stensorflow/cops/_stf_int64pooling_macos.so
stensorflow/cops/_stf_random_linux.so
stensorflow/cops/_stf_random_macos.so
stensorflow/cops/test_homo.py
stensorflow/engine/__init__.py
stensorflow/engine/float_compute.py
stensorflow/engine/float_compute_narrow.py
stensorflow/engine/start_server.py
stensorflow/exception/__init__.py
stensorflow/exception/exception.py
stensorflow/homo_enc/__init__.py
stensorflow/homo_enc/homo_enc.py
stensorflow/homo_enc/homo_mat_mul.py
morse_stf-0.1.36.dist-info/METADATA
morse_stf-0.1.36.dist-info/WHEEL
morse_stf-0.1.36.dist-info/entry_points.txt
morse_stf-0.1.36.dist-info/top_level.txt
morse_stf-0.1.36.dist-info/RECORD
